pytritech/__init__.py
pytritech/ciheader.py
pytritech/glf.py
pytritech/glftimes.py
pytritech/image.py
pytritech/status.py
pytritech/util/range.py
pytritech/util/time.py
pytritech-1.0.2.dist-info/WHEEL
pytritech-1.0.2.dist-info/METADATA
pytritech-1.0.2.dist-info/RECORD
