Metadata-Version: 2.1
Name: pytritech
Version: 1.0.2
Summary: A Python interface to Tritech Gemini Sonar files.
Author-email: Benjamin James Blundell <me@benjamin.computer>
Requires-Python: >=3.8
Classifier: Development Status :: 5 - Production/Stable
Classifier: License :: OSI Approved :: GNU General Public License v3 (GPLv3)
Classifier: Natural Language :: English
Classifier: Operating System :: OS Independent
Classifier: Programming Language :: Python
Classifier: Programming Language :: Python :: 3.8
Classifier: Programming Language :: Python :: 3.9
Requires-Dist: pytz
Requires-Dist: isal
Requires-Dist: zipfile-isal
Requires-Dist: tox ; extra == "dev"
Requires-Dist: pre-commit ; extra == "dev"
Requires-Dist: bump2version ; extra == "dev"
Requires-Dist: mkdocs ; extra == "dev"
Requires-Dist: mkdocstrings-python ; extra == "dev"
Requires-Dist: pyinstrument ; extra == "dev"
Requires-Dist: GitPython ; extra == "dev"
Requires-Dist: pillow ; extra == "dev"
Requires-Dist: pytest ; extra == "test"
Project-URL: Bug Tracker, https://github.com/onidaito/pytritech/issues
Project-URL: Homepage, https://github.com/onidaito/pytritech
Provides-Extra: dev
Provides-Extra: test
